GrammarFixAPI/__init__.py
GrammarFixAPI/app.py
GrammarFixAPI/static/script.js
GrammarFixAPI/static/style.css
GrammarFixAPI/templates/index.html
GrammarFixAPI-0.1.0.dist-info/METADATA
GrammarFixAPI-0.1.0.dist-info/WHEEL
GrammarFixAPI-0.1.0.dist-info/entry_points.txt
GrammarFixAPI-0.1.0.dist-info/top_level.txt
GrammarFixAPI-0.1.0.dist-info/RECORD
