Metadata-Version: 2.1
Name: GrammarFixAPI
Version: 0.1.0
Summary: Grammar checking using Ai
Home-page: https://github.com/projectest20/GrammarFixAPI
Author: projectest20
Author-email: projecttest021010@gmail.com
Classifier: Programming Language :: Python :: 3
Classifier: Operating System :: OS Independent
Requires-Python: >=3.6
